vconnector/__init__.py
vconnector/vertica_connector.py
vconnector/vertica_insert.py
vconnector/vertica_merge.py
vertica_connector_talenttech-1.2.1.dist-info/LICENSE.txt
vertica_connector_talenttech-1.2.1.dist-info/METADATA
vertica_connector_talenttech-1.2.1.dist-info/WHEEL
vertica_connector_talenttech-1.2.1.dist-info/top_level.txt
vertica_connector_talenttech-1.2.1.dist-info/RECORD
