Metadata-Version: 2.1
Name: vertica-connector-talenttech
Version: 1.2.1
Summary: TopMind Vertica Connector Wrapper
Home-page: https://github.com/severgroup-tt/topmind-commons/py/vertica-connector
Author: Dmitry Utiralov
Author-email: d.utiralov@talenttech.ru
License: MIT
Classifier: Programming Language :: Python :: 3
Classifier: License :: OSI Approved :: MIT License
Classifier: Operating System :: OS Independent
Requires-Python: >=3.6
License-File: LICENSE.txt
Requires-Dist: vertica-python
